{
    "id": "baur2017bitcoin",
    "title": "Bitcoin: Medium Of Exchange Or Speculative Assets?",
    "year": 2017,
    "type": "article",
    "sortkey": 20180108,
    "authors": [
        {
            "affiliation": "",
            "name": "Dirk G Baur"
        },
        {
            "affiliation": "",
            "name": "KiHoon Hong"
        },
        {
            "affiliation": "",
            "name": "Adrian D Lee"
        }
    ],
    "url": null,
    "venue": "Journal of International Financial Markets, Institutions and Money",
    "peer-reviewed": true,
    "abstract": ""
}