{
    "id": "chatterjeebitcoin",
    "title": "Bitcoin Exclusively Informational Money: A Valuable Review From 2010 To 2017",
    "year": 2017,
    "type": "article",
    "sortkey": 20171023,
    "authors": [
        {
            "affiliation": "",
            "name": "Jyotir Moy Chatterjee"
        },
        {
            "affiliation": "",
            "name": "Srijani Ghatak"
        },
        {
            "affiliation": "",
            "name": "Raghvendra Kumar"
        },
        {
            "affiliation": "",
            "name": "Manju Khari"
        },
        {
            "affiliation": "",
            "name": "others"
        }
    ],
    "url": "https://link.springer.com/article/10.1007/s11135-017-0605-5",
    "venue": "Quality \\& Quantity",
    "peer-reviewed": true,
    "abstract": ""
}