{
    "id": "cocco2017banking",
    "title": "Banking On Blockchain: Costs Savings Thanks To The Blockchain Technology",
    "year": 2017,
    "type": "article",
    "sortkey": 20170702,
    "authors": [
        {
            "affiliation": "",
            "name": "Luisanna Cocco"
        },
        {
            "affiliation": "",
            "name": "Andrea Pinna"
        },
        {
            "affiliation": "",
            "name": "Michele Marchesi"
        }
    ],
    "url": "http://www.mdpi.com/1999-5903/9/3/25",
    "venue": "Future Internet",
    "peer-reviewed": true,
    "abstract": ""
}