{
    "id": "voets2017blockchain",
    "title": "Blockchain Technology In The Energy Ecosystem: An Explorative Study On The Disruptive Power Of Blockchain Technology In The Dutch Energy Ecosystem",
    "year": 2017,
    "type": "article",
    "sortkey": 20170919,
    "authors": [
        {
            "affiliation": "",
            "name": "Amber Voets"
        }
    ],
    "url": "https://repository.tudelft.nl/islandora/object/uuid:ce37e094-cf9e-4976-afde-2e0ecdf8880a",
    "peer-reviewed": false,
    "abstract": ""
}